{"warnings":[{"file":"/Users/ljunf/repos/Nanomsg.swift/Sources/Flags.swift","line":3,"symbol":"None","symbol_kind":"source.lang.swift.decl.enumelement","warning":"undocumented"},{"file":"/Users/ljunf/repos/Nanomsg.swift/Sources/Flags.swift","line":4,"symbol":"Dontwait","symbol_kind":"source.lang.swift.decl.enumelement","warning":"undocumented"},{"file":"/Users/ljunf/repos/Nanomsg.swift/Sources/NanomsgError.swift","line":9,"symbol":"NanomsgError","symbol_kind":"source.lang.swift.decl.enum","warning":"undocumented"},{"file":"/Users/ljunf/repos/Nanomsg.swift/Sources/NanomsgError.swift","line":10,"symbol":"Err","symbol_kind":"source.lang.swift.decl.enumelement","warning":"undocumented"},{"file":"/Users/ljunf/repos/Nanomsg.swift/Sources/WSMsgType.swift","line":3,"symbol":"Text","symbol_kind":"source.lang.swift.decl.enumelement","warning":"undocumented"},{"file":"/Users/ljunf/repos/Nanomsg.swift/Sources/WSMsgType.swift","line":4,"symbol":"Binary","symbol_kind":"source.lang.swift.decl.enumelement","warning":"undocumented"}],"source_directory":"/Users/ljunf/repos/Nanomsg.swift"}